link2proxy/__init__.py
link2proxy-0.1.0.dist-info/METADATA
link2proxy-0.1.0.dist-info/WHEEL
link2proxy-0.1.0.dist-info/top_level.txt
link2proxy-0.1.0.dist-info/RECORD
