Metadata-Version: 2.4
Name: link2proxy
Version: 0.1.0
Summary: Get proxies for free and automatically without any hassle.
Home-page: https://github.com/zZarby/link2proxy
Author: Zarby
Author-email: 
Classifier: Programming Language :: Python :: 3
Classifier: License :: OSI Approved :: MIT License
Classifier: Operating System :: OS Independent
Requires-Python: >=3.6
Dynamic: author
Dynamic: classifier
Dynamic: description
Dynamic: description-content-type
Dynamic: home-page
Dynamic: requires-python
Dynamic: summary
